consul/__init__.py
consul/aio.py
consul/base.py
consul/std.py
consul/tornado.py
consul/twisted.py
viant_python_consul-1.1.2.dist-info/LICENSE
viant_python_consul-1.1.2.dist-info/METADATA
viant_python_consul-1.1.2.dist-info/WHEEL
viant_python_consul-1.1.2.dist-info/top_level.txt
viant_python_consul-1.1.2.dist-info/RECORD
