Metadata-Version: 2.1
Name: viant-python-consul
Version: 1.1.2
Summary: Python client for Consul (http://www.consul.io/)
Home-page: https://github.com/cablehead/python-consul
Author: Andy Gayton
Author-email: andy@thecablelounge.com
License: MIT
Platform: UNKNOWN
Classifier: Development Status :: 3 - Alpha
Classifier: Intended Audience :: Developers
Classifier: License :: OSI Approved :: MIT License
Classifier: Programming Language :: Python :: 2
Classifier: Programming Language :: Python :: 2.7
Classifier: Programming Language :: Python :: 3
Classifier: Programming Language :: Python :: 3.5
Classifier: Programming Language :: Python :: 3.6
Requires-Dist: requests (>=2.0)
Requires-Dist: six (>=1.4)
Provides-Extra: asyncio
Requires-Dist: aiohttp ; extra == 'asyncio'
Provides-Extra: tornado
Requires-Dist: tornado ; extra == 'tornado'
Provides-Extra: twisted
Requires-Dist: twisted ; extra == 'twisted'
Requires-Dist: treq ; extra == 'twisted'
